{
    "universities" : {
        
        "jacobs" : {
            "holidays" : 
            [
                {
                    "start" : "2019-01-01",
                    "end" : "2019-01-07"
                },
                {
                    "start" : "2019-03-26",
                    "end" : "2019-04-02"
                }
            ],
            "location" : "germany",
            "code" : "de"    
        },
    
    
        "upc" : {
            "holidays" : 
            [
                {
                    "start" : "2019-01-01",
                    "end" : "2019-01-07"
                },
                {
                    "start" : "2019-03-26",
                    "end" : "2019-04-02"
                }
            ],
            "location" : "spain",
            "code" : "es"    
        }
    }
}
